LICENCE
README.md
pyproject.toml
setup.cfg
setup.py
src/badd/__init__.py
src/badd.egg-info/PKG-INFO
src/badd.egg-info/SOURCES.txt
src/badd.egg-info/dependency_links.txt
src/badd.egg-info/requires.txt
src/badd.egg-info/top_level.txt
src/badd/ad/__init__.py
src/badd/ad/ad_detector.py
src/badd/ad/ad_model.py
src/badd/file_loader/__init__.py
src/badd/file_loader/file_loader.py
src/badd/obscene/__init__.py
src/badd/obscene/obscene_detector.py
src/badd/obscene/obscene_model.py
src/badd/toxic/__init__.py
src/badd/toxic/toxic_detector.py
src/badd/toxic/toxic_model.py