Metadata-Version: 2.1
Name: badd
Version: 1.0.32
Summary: In English
Home-page: https://github.com/wksmirnowa/badd
Author: Vladislava Smirnova
Author-email: wksmirnowa@gmail.com
License: MIT
Keywords: toxic ad advertising obscene classification texts words nlp nn
Platform: UNKNOWN
Requires-Python: >=3.7.*
License-File: LICENCE
